intelligent_automl/__init__.py
intelligent_automl/cli.py
intelligent_automl/complete_framework.py
intelligent_automl/version.py
intelligent_automl/core/__init__.py
intelligent_automl/core/base.py
intelligent_automl/core/config.py
intelligent_automl/core/exceptions.py
intelligent_automl/core/types.py
intelligent_automl/data/__init__.py
intelligent_automl/data/loaders.py
intelligent_automl/data/pipeline.py
intelligent_automl/data/preprocessors.py
intelligent_automl/evaluation/__init__.py
intelligent_automl/evaluation/multi_metric_evaluator.py
intelligent_automl/intelligence/__init__.py
intelligent_automl/intelligence/pipeline_selector.py
intelligent_automl/models/__init__.py
intelligent_automl/models/auto_trainer.py
intelligent_automl/utils/__init__.py
intelligent_automl/utils/logging.py
intelligent_automl/utils/validation.py
intelligent_automl-1.1.2.dist-info/licenses/LICENSE
intelligent_automl-1.1.2.dist-info/METADATA
intelligent_automl-1.1.2.dist-info/WHEEL
intelligent_automl-1.1.2.dist-info/entry_points.txt
intelligent_automl-1.1.2.dist-info/top_level.txt
intelligent_automl-1.1.2.dist-info/RECORD
