Metadata-Version: 2.4
Name: intelligent-automl
Version: 1.1.2
Summary: Intelligent AutoML Framework with comprehensive multi-metric evaluation and AI-driven optimization
Home-page: https://github.com/AhmedMansour1070/intelligent-automl
Author: Ahmed Mansour
Author-email: your.email@example.com
License: MIT
Project-URL: Bug Tracker, https://github.com/AhmedMansour1070/intelligent-automl/issues
Project-URL: Documentation, https://github.com/AhmedMansour1070/intelligent-automl/docs
Project-URL: Source Code, https://github.com/AhmedMansour1070/intelligent-automl
Keywords: automl,machine-learning,artificial-intelligence,data-science,automated-ml,hyperparameter-optimization,feature-engineering,model-selection,multi-objective-optimization,pareto-optimization
Platform: any
Classifier: Development Status :: 4 - Beta
Classifier: Intended Audience :: Developers
Classifier: Intended Audience :: Science/Research
Classifier: Intended Audience :: Education
Classifier: License :: OSI Approved :: MIT License
Classifier: Operating System :: OS Independent
Classifier: Programming Language :: Python :: 3
Classifier: Programming Language :: Python :: 3.8
Classifier: Programming Language :: Python :: 3.9
Classifier: Programming Language :: Python :: 3.10
Classifier: Programming Language :: Python :: 3.11
Classifier: Programming Language :: Python :: 3.12
Classifier: Topic :: Scientific/Engineering :: Artificial Intelligence
Classifier: Topic :: Software Development :: Libraries :: Python Modules
Classifier: Topic :: Scientific/Engineering :: Information Analysis
Classifier: Typing :: Typed
Requires-Python: >=3.8
License-File: LICENSE
Requires-Dist: pandas>=1.3.0
Requires-Dist: numpy>=1.21.0
Requires-Dist: scikit-learn>=1.1.0
Requires-Dist: matplotlib>=3.5.0
Requires-Dist: seaborn>=0.11.0
Requires-Dist: scipy>=1.7.0
Requires-Dist: joblib>=1.1.0
Requires-Dist: click>=8.0.0
Requires-Dist: tqdm>=4.62.0
Requires-Dist: pydantic>=1.9.0
Requires-Dist: python-json-logger>=2.0.0
Requires-Dist: colorlog>=6.6.0
Requires-Dist: python-dotenv>=0.19.0
Provides-Extra: full
Requires-Dist: xgboost>=1.6.0; extra == "full"
Requires-Dist: lightgbm>=3.3.0; extra == "full"
Requires-Dist: catboost>=1.0.0; extra == "full"
Requires-Dist: optuna>=2.10.0; extra == "full"
Requires-Dist: scikit-optimize>=0.9.0; extra == "full"
Provides-Extra: dev
Requires-Dist: pytest>=6.0; extra == "dev"
Requires-Dist: pytest-cov>=2.0; extra == "dev"
Requires-Dist: black>=21.0; extra == "dev"
Requires-Dist: flake8>=3.8; extra == "dev"
Requires-Dist: mypy>=0.910; extra == "dev"
Requires-Dist: sphinx>=4.0.0; extra == "dev"
Requires-Dist: sphinx-rtd-theme>=1.0.0; extra == "dev"
Requires-Dist: twine>=3.0.0; extra == "dev"
Requires-Dist: wheel>=0.37.0; extra == "dev"
Provides-Extra: docs
Requires-Dist: sphinx>=4.0.0; extra == "docs"
Requires-Dist: sphinx-rtd-theme>=1.0.0; extra == "docs"
Requires-Dist: myst-parser>=0.16.0; extra == "docs"
Requires-Dist: sphinx-autoapi>=1.8.0; extra == "docs"
Provides-Extra: all
Requires-Dist: optuna>=2.10.0; extra == "all"
Requires-Dist: sphinx-autoapi>=1.8.0; extra == "all"
Requires-Dist: pytest>=6.0; extra == "all"
Requires-Dist: catboost>=1.0.0; extra == "all"
Requires-Dist: black>=21.0; extra == "all"
Requires-Dist: lightgbm>=3.3.0; extra == "all"
Requires-Dist: sphinx>=4.0.0; extra == "all"
Requires-Dist: wheel>=0.37.0; extra == "all"
Requires-Dist: pytest-cov>=2.0; extra == "all"
Requires-Dist: twine>=3.0.0; extra == "all"
Requires-Dist: xgboost>=1.6.0; extra == "all"
Requires-Dist: flake8>=3.8; extra == "all"
Requires-Dist: scikit-optimize>=0.9.0; extra == "all"
Requires-Dist: mypy>=0.910; extra == "all"
Requires-Dist: sphinx-rtd-theme>=1.0.0; extra == "all"
Requires-Dist: myst-parser>=0.16.0; extra == "all"
Dynamic: author
Dynamic: author-email
Dynamic: classifier
Dynamic: description
Dynamic: description-content-type
Dynamic: home-page
Dynamic: keywords
Dynamic: license
Dynamic: license-file
Dynamic: platform
Dynamic: project-url
Dynamic: provides-extra
Dynamic: requires-dist
Dynamic: requires-python
Dynamic: summary
